{
	"name": "SpinStarter",
	"image": "mcr.microsoft.com/devcontainers/base:noble",
	"features": {
		"ghcr.io/devcontainers/features/node:1": {
			"nodeGypDependencies": true,
			"installYarnUsingApt": false,
			"version": "24.10.0",
			"pnpmVersion": "none",
			"nvmVersion": "latest"
		},
		"ghcr.io/devcontainers/features/python:1": {
			"installTools": true,
			"version": "3.14.0"
		},
		"ghcr.io/devcontainers/features/go:1": {
			"version": "1.25.2"
		},
		"ghcr.io/devcontainers/features/rust:1": {
			"version": "1.89.0",
			"profile": "minimal",
			"targets": "wasm32-wasip1",
			"components": "rust-analyzer,rust-src,rustfmt,clippy"
		},
		"ghcr.io/thorstenhans/devcontainer-features/tinygo:latest": {},
		"ghcr.io/thorstenhans/devcontainer-features/spin:latest": {}
	},
	"forwardPorts": [
		3000
	]
	// Use 'postCreateCommand' to run commands after the container is created.
	// "postCreateCommand": "uname -a",
	// Configure tool-specific properties.
	// "customizations": {},
	// Uncomment to connect as root instead. More info: https://aka.ms/dev-containers-non-root.
	// "remoteUser": "root"
}